README.md
setup.py
houstonj2013_ml/KNearestNeighbors.py
houstonj2013_ml/Kmeans.py
houstonj2013_ml/Logistic_Regression.py
houstonj2013_ml/NMF.py
houstonj2013_ml/__init__.py
houstonj2013_ml/ctree.py
houstonj2013_ml/cyfun.c
houstonj2013_ml/plot_tree.py
houstonj2013_ml/roc.py
houstonj2013_ml/setup.py
houstonj2013_ml/tree.py
houstonj2013_ml/tree_v2.py
houstonj2013_ml.egg-info/PKG-INFO
houstonj2013_ml.egg-info/SOURCES.txt
houstonj2013_ml.egg-info/dependency_links.txt
houstonj2013_ml.egg-info/not-zip-safe
houstonj2013_ml.egg-info/top_level.txt