Metadata-Version: 1.0
Name: houstonj2013-ml
Version: 1.0
Summary: houstonj2013 machine learning modules
Home-page: http://github.com/HoustonJ2013/HoustonJ2013_ml
Author: Jingbo Liu
Author-email: jingbo.liu2013@gmail.com
License: selfie
Platform: UNKNOWN
